mt_researcher/README.md
mt_researcher/__init__.py
mt_researcher/config/__init__.py
mt_researcher/config/config.py
mt_researcher/context/__init__.py
mt_researcher/context/compression.py
mt_researcher/context/retriever.py
mt_researcher/document/__init__.py
mt_researcher/document/document.py
mt_researcher/document/langchain_document.py
mt_researcher/llm_provider/__init__.py
mt_researcher/llm_provider/anthropic/__init__.py
mt_researcher/llm_provider/anthropic/anthropic.py
mt_researcher/llm_provider/azureopenai/__init__.py
mt_researcher/llm_provider/azureopenai/azureopenai.py
mt_researcher/llm_provider/generic/__init__.py
mt_researcher/llm_provider/generic/base.py
mt_researcher/llm_provider/google/__init__.py
mt_researcher/llm_provider/google/google.py
mt_researcher/llm_provider/groq/__init__.py
mt_researcher/llm_provider/groq/groq.py
mt_researcher/llm_provider/huggingface/__init__.py
mt_researcher/llm_provider/huggingface/huggingface.py
mt_researcher/llm_provider/mistral/__init__.py
mt_researcher/llm_provider/mistral/mistral.py
mt_researcher/llm_provider/ollama/__init__.py
mt_researcher/llm_provider/ollama/ollama.py
mt_researcher/llm_provider/openai/__init__.py
mt_researcher/llm_provider/openai/openai.py
mt_researcher/llm_provider/together/__init__.py
mt_researcher/llm_provider/together/together.py
mt_researcher/llm_provider/unify/__init__.py
mt_researcher/llm_provider/unify/unify.py
mt_researcher/master/__init__.py
mt_researcher/master/actions.py
mt_researcher/master/agent.py
mt_researcher/master/prompts.py
mt_researcher/memory/__init__.py
mt_researcher/memory/embeddings.py
mt_researcher/retrievers/__init__.py
mt_researcher/retrievers/arxiv/__init__.py
mt_researcher/retrievers/arxiv/arxiv.py
mt_researcher/retrievers/bing/__init__.py
mt_researcher/retrievers/bing/bing.py
mt_researcher/retrievers/custom/__init__.py
mt_researcher/retrievers/custom/custom.py
mt_researcher/retrievers/duckduckgo/__init__.py
mt_researcher/retrievers/duckduckgo/duckduckgo.py
mt_researcher-0.3.3.dist-info/LICENSE--
mt_researcher-0.3.3.dist-info/METADATA
mt_researcher-0.3.3.dist-info/WHEEL
mt_researcher-0.3.3.dist-info/RECORD
