Metadata-Version: 2.1
Name: mt_researcher
Version: 0.3.3
Summary: MT Researcher is an autonomous agent designed for comprehensive online research on a variety of tasks.
License: MIT
Author: Assaf Elovic
Author-email: assaf.elovic@gmail.com
Requires-Python: >=3.10,<3.12
Classifier: License :: OSI Approved :: MIT License
Classifier: Programming Language :: Python :: 3
Classifier: Programming Language :: Python :: 3.10
Classifier: Programming Language :: Python :: 3.11
Requires-Dist: PyMuPDF (>=1.23.6)
Requires-Dist: SQLAlchemy (>=2.0.28)
Requires-Dist: aiofiles (>=23.2.1)
Requires-Dist: arxiv (>=2.0.0)
Requires-Dist: beautifulsoup4 (>=4.12.2)
Requires-Dist: colorama (>=0.4.6)
Requires-Dist: datasets (>=2.20.0,<3.0.0)
Requires-Dist: duckduckgo_search (>=4.1.1)
Requires-Dist: fastapi (>=0.104.1)
Requires-Dist: htmldocx (>=0.0.6,<0.0.7)
Requires-Dist: jinja2 (>=3.1.2)
Requires-Dist: json-repair (>=0.25.3,<0.26.0)
Requires-Dist: json5 (>=0.9.25,<0.10.0)
Requires-Dist: langchain (>=0.2,<0.3)
Requires-Dist: langchain-google-genai (>=1,<2)
Requires-Dist: langchain-huggingface (>=0.0.3,<0.0.4)
Requires-Dist: langchain-openai (>=0.1,<0.2)
Requires-Dist: langchain_community (>=0.2,<0.3)
Requires-Dist: langgraph (>=0.0.29,<0.1)
Requires-Dist: lxml[html-clean] (>=4.9.2)
Requires-Dist: markdown (>=3.5.1)
Requires-Dist: md2pdf (>=1.0.1)
Requires-Dist: mistune (>=3.0.2,<4.0.0)
Requires-Dist: newspaper3k (>=0.2.8)
Requires-Dist: openai (>=1.3.3)
Requires-Dist: optimum[onnxruntime-gpu] (>=1.21.2,<2.0.0)
Requires-Dist: permchain (>=0.0.6)
Requires-Dist: playwright (>=1.39.0)
Requires-Dist: pydantic (>=2.5.1)
Requires-Dist: python-docx (>=1.1.0,<2.0.0)
Requires-Dist: python-dotenv (>=1.0.0)
Requires-Dist: python-multipart (>=0.0.6)
Requires-Dist: pyyaml (>=6.0.1)
Requires-Dist: requests (>=2.31.0)
Requires-Dist: scikit-learn (>=1.5.1,<2.0.0)
Requires-Dist: tavily-python (>=0.2.8)
Requires-Dist: tiktoken (>=0.7.0)
Requires-Dist: transformers (>=4.42.4,<5.0.0)
Requires-Dist: unstructured (>=0.13.0,<0.14.0)
Requires-Dist: uvicorn (>=0.24.0.post1)
